pachyderm/__init__.py
pachyderm/_version.py
pachyderm/_version.pyi
pachyderm/binned_data.py
pachyderm/generic_class.py
pachyderm/generic_config.py
pachyderm/histogram.py
pachyderm/plot.py
pachyderm/projectors.py
pachyderm/py.typed
pachyderm/remove_outliers.py
pachyderm/typing_helpers.py
pachyderm/utils.py
pachyderm/yaml.py
pachyderm/alice/__init__.py
pachyderm/alice/download.py
pachyderm/alice/utils.py
pachyderm/alice/datasets/__init__.py
pachyderm/alice/datasets/lhc16j5.yaml
pachyderm/alice/datasets/lhc17p.yaml
pachyderm/alice/datasets/lhc18q.yaml
pachyderm/alice/datasets/lhc18r.yaml
pachyderm/alice/datasets/lhc19f4.yaml
pachyderm/alice/datasets/lhc20g4.yaml
pachyderm/fit/__init__.py
pachyderm/fit/base.py
pachyderm/fit/cost_function.py
pachyderm/fit/function.py
pachyderm/fit/integration.py
pachyderm/test_fixtures/__init__.py
pachyderm/test_fixtures/logging.py
pachyderm/test_fixtures/objects.py
pachyderm-3.2.2.dist-info/METADATA
pachyderm-3.2.2.dist-info/WHEEL
pachyderm-3.2.2.dist-info/entry_points.txt
pachyderm-3.2.2.dist-info/licenses/LICENSE
pachyderm-3.2.2.dist-info/RECORD
