Metadata-Version: 2.1
Name: pachyderm
Version: 3.2.2
Summary: Physics Analysis Core for Heavy-Ions
Project-URL: Homepage, https://github.com/raymondEhlers/pachyderm
Project-URL: Bug Tracker, https://github.com/raymondEhlers/pachyderm/issues
Project-URL: Discussions, https://github.com/raymondEhlers/pachyderm/discussions
Project-URL: Changelog, https://github.com/raymondEhlers/pachyderm/releases
Author-email: Raymond Ehlers <raymond.ehlers@cern.ch>
License: BSD 3-Clause License
License-File: LICENSE
Classifier: Development Status :: 5 - Production/Stable
Classifier: Intended Audience :: Developers
Classifier: Intended Audience :: Science/Research
Classifier: License :: OSI Approved :: BSD License
Classifier: Operating System :: OS Independent
Classifier: Programming Language :: Python
Classifier: Programming Language :: Python :: 3
Classifier: Programming Language :: Python :: 3 :: Only
Classifier: Programming Language :: Python :: 3.10
Classifier: Programming Language :: Python :: 3.11
Classifier: Programming Language :: Python :: 3.12
Classifier: Topic :: Scientific/Engineering
Classifier: Typing :: Typed
Requires-Python: >=3.10
Requires-Dist: attrs>=21.2.0
Requires-Dist: iminuit>=2.7.0
Requires-Dist: matplotlib>=3.3.2
Requires-Dist: numdifftools>=0.9.40
Requires-Dist: numpy>=1.21
Requires-Dist: ruamel-yaml>=0.17.10
Requires-Dist: scipy>=1.7.0
Provides-Extra: dev
Requires-Dist: boost-histogram>=1.2.1; extra == 'dev'
Requires-Dist: hist>=2.7.1; extra == 'dev'
Requires-Dist: mypy>=0.931; extra == 'dev'
Requires-Dist: pre-commit>=2.13.0; extra == 'dev'
Requires-Dist: pytest-cov>=3; extra == 'dev'
Requires-Dist: pytest-mock>=3.6.1; extra == 'dev'
Requires-Dist: pytest-sugar>=1.0.0; extra == 'dev'
Requires-Dist: pytest-xdist>=3.5.0; extra == 'dev'
Requires-Dist: pytest>=6; extra == 'dev'
Requires-Dist: ruff>=0.0.209; extra == 'dev'
Requires-Dist: uproot>=4; extra == 'dev'
Provides-Extra: docs
Requires-Dist: furo>=2023.08.17; extra == 'docs'
Requires-Dist: myst-parser>=0.13; extra == 'docs'
Requires-Dist: sphinx-autodoc-typehints; extra == 'docs'
Requires-Dist: sphinx-copybutton; extra == 'docs'
Requires-Dist: sphinx>=7.0; extra == 'docs'
Provides-Extra: test
Requires-Dist: pytest-cov>=3; extra == 'test'
Requires-Dist: pytest-mock>=3.6.1; extra == 'test'
Requires-Dist: pytest-sugar>=1.0.0; extra == 'test'
Requires-Dist: pytest-xdist>=3.5.0; extra == 'test'
Requires-Dist: pytest>=6; extra == 'test'
